[
    {
        "nimi": "Afganistan",
        "pealinn": "Kabul"
    },
    {
        "nimi": "Albaania",
        "pealinn": "Tirana"
    },
    {
        "nimi": "Alžeeria",
        "pealinn": "Alžiir"
    },
    {
        "nimi": "Ameerika Ühendriigid",
        "pealinn": "Washington"        
    },
    {
        "nimi": "Andorra",
        "pealinn": "Andorra la Vella"        
    },
    {
        "nimi": "Angola",
        "pealinn": "Luanda"        
    },
    {
        "nimi": "Antigua ja Barbuda",
        "pealinn": "Saint John's"        
    },
    {
        "nimi": "Araabia Ühendemiraadid",
        "pealinn": "Abu Dhabi"        
    },
    {
        "nimi": "Argentiina",
        "pealinn": "Buenos Aires"        
    },
    {
        "nimi": "Armeenia",
        "pealinn": "Jerevan"        
    },
    {
        "nimi": "Aserbaidžaan",
        "pealinn": "Bakuu"        
    },
    {
        "nimi": "Austraalia",
        "pealinn": "Canberra"        
    },
    {
        "nimi": "Austria",
        "pealinn": "Viin"        
    }
  ]